dessia_api_client/__init__.py
dessia_api_client/clients.py
dessia_api_client/users.py
dessia_api_client/endpoints/__init__.py
dessia_api_client/endpoints/accounts.py
dessia_api_client/endpoints/admin.py
dessia_api_client/endpoints/applications.py
dessia_api_client/endpoints/classes.py
dessia_api_client/endpoints/distributions.py
dessia_api_client/endpoints/files.py
dessia_api_client/endpoints/jobs.py
dessia_api_client/endpoints/marketplace.py
dessia_api_client/endpoints/objects.py
dessia_api_client/endpoints/organisations.py
dessia_api_client/endpoints/style.py
dessia_api_client/endpoints/workspaces.py
dessia_api_client/utils/__init__.py
dessia_api_client/utils/exceptions.py
dessia_api_client/utils/filters.py
dessia_api_client/utils/helpers.py
dessia_api_client-0.4.2.dist-info/LICENSE
dessia_api_client-0.4.2.dist-info/METADATA
dessia_api_client-0.4.2.dist-info/WHEEL
dessia_api_client-0.4.2.dist-info/top_level.txt
dessia_api_client-0.4.2.dist-info/RECORD
