Metadata-Version: 2.1
Name: dessia-api-client
Version: 0.4.2
Summary: Python client to interact with DessiA API
Home-page: UNKNOWN
Author: DessiA Technologies
Author-email: root@dessia.tech
License: UNKNOWN
Platform: UNKNOWN
Requires-Dist: PyJWT (>=2.0.0)
Requires-Dist: requests
Requires-Dist: matplotlib
Requires-Dist: simplejson
